{
  "banner_image": "about-banner.jpg",
  "about_us_heading": "About Our Creative Agency",
  "about_us_text": "Identity Wind is a collective of passionate designers, developers, and strategists dedicated to crafting unique and impactful digital experiences. We believe in the power of great design to transform businesses and connect with audiences in meaningful ways. Our mission is to bring your vision to life with creativity, precision, and a commitment to excellence.",
  "about_us_image": "company-photo.jpg",
  "who_we_are_heading": "Who We Are?",
  "who_we_are_text": "Founded in 2024, our journey began with a simple goal: to create beautiful, functional websites and brand identities that stand out. We thrive on collaboration and are driven by the success of our clients. From small startups to established enterprises, we approach every project with the same level of dedication and enthusiasm, ensuring results that not only look good but also drive growth."
}